proxycycle/Proxy.py
proxycycle/ProxySet.py
proxycycle/__init__.py
proxycycle/filters.py
proxycycle/api/__init__.py
proxycycle/api/proxyscrape.py
proxycycle/cli/fetch_proxy.py
proxycycle/enums/__init__.py
proxycycle/enums/anonymity_level.py
proxycycle/enums/scheme.py
proxycycle-2.0.1.dist-info/METADATA
proxycycle-2.0.1.dist-info/WHEEL
proxycycle-2.0.1.dist-info/entry_points.txt
proxycycle-2.0.1.dist-info/licenses/LICENSE.txt
proxycycle-2.0.1.dist-info/RECORD
