Metadata-Version: 2.4
Name: proxycycle
Version: 2.0.1
Summary: A Library to easily load/fetch proxy servers.
Project-URL: Documentation, https://github.com/Vbrawl/proxycycle#readme
Project-URL: Issues, https://github.com/Vbrawl/proxycycle/issues
Project-URL: Source, https://github.com/Vbrawl/proxycycle
Author-email: Vbrawl <greninjagr@gmail.com>
License-Expression: MIT
License-File: LICENSE.txt
Classifier: Programming Language :: Python
Classifier: Programming Language :: Python :: 3.10
Classifier: Programming Language :: Python :: 3.11
Classifier: Programming Language :: Python :: 3.12
Classifier: Programming Language :: Python :: Implementation :: PyPy
Requires-Python: >=3.10
Requires-Dist: aiohttp
Requires-Dist: aiohttp-socks
Requires-Dist: requests
